dyn_cli-0.1.0.dist-info/METADATA
dyn_cli-0.1.0.dist-info/RECORD
dyn_cli-0.1.0.dist-info/WHEEL
dyn_cli-0.1.0.dist-info/entry_points.txt
dyn_cli-0.1.0.dist-info/top_level.txt
dyncli/__init__.py
dyncli/__main__.py
dyncli/cli.py
dyncli/commands/__init__.py
dyncli/commands/base.py
dyncli/commands/create_table.py
dyncli/commands/delete_table.py
dyncli/commands/list_tables.py
dyncli/commands/update_table.py
