Metadata-Version: 2.1
Name: dyn-cli
Version: 0.1.0
Summary: Dyn CLI - DynamoDB Command Line Interface
Home-page: https://github.com/henriquemenezes/dyn-cli
Author: Henrique Menezes
Author-email: hamsalmeida@gmail.com
License: Apache License 2.0
Platform: UNKNOWN
Classifier: Development Status :: 3 - Alpha
Classifier: Environment :: Console
Classifier: Intended Audience :: Developers
Classifier: Intended Audience :: System Administrators
Classifier: License :: OSI Approved :: Apache Software License
Classifier: Natural Language :: English
Classifier: Operating System :: MacOS
Classifier: Operating System :: Microsoft :: Windows
Classifier: Operating System :: POSIX
Classifier: Operating System :: Unix
Classifier: Programming Language :: Python
Classifier: Programming Language :: Python :: 2
Classifier: Programming Language :: Python :: 2.6
Classifier: Programming Language :: Python :: 2.7
Classifier: Programming Language :: Python :: 3
Classifier: Programming Language :: Python :: 3.3
Classifier: Programming Language :: Python :: 3.4
Classifier: Programming Language :: Python :: 3.5
Classifier: Programming Language :: Python :: 3.6
Classifier: Topic :: Database
Classifier: Topic :: Terminals
Classifier: Topic :: Utilities
Requires-Dist: boto3 (==1.4.4)
Requires-Dist: botocore (==1.5.65)
Requires-Dist: click (==6.7)
Requires-Dist: colorama (==0.3.9)
Requires-Dist: docutils (==0.13.1)
Requires-Dist: futures (==3.1.1)
Requires-Dist: jmespath (==0.9.3)
Requires-Dist: python-dateutil (==2.6.0)
Requires-Dist: s3transfer (==0.1.10)
Requires-Dist: six (==1.10.0)
